openpyexcel/__init__.py
openpyexcel/_constants.py
openpyexcel/conftest.py
openpyexcel/cell/__init__.py
openpyexcel/cell/cell.py
openpyexcel/cell/interface.py
openpyexcel/cell/read_only.py
openpyexcel/cell/text.py
openpyexcel/chart/_3d.py
openpyexcel/chart/__init__.py
openpyexcel/chart/_chart.py
openpyexcel/chart/area_chart.py
openpyexcel/chart/axis.py
openpyexcel/chart/bar_chart.py
openpyexcel/chart/bubble_chart.py
openpyexcel/chart/chartspace.py
openpyexcel/chart/data_source.py
openpyexcel/chart/descriptors.py
openpyexcel/chart/error_bar.py
openpyexcel/chart/label.py
openpyexcel/chart/layout.py
openpyexcel/chart/legend.py
openpyexcel/chart/line_chart.py
openpyexcel/chart/marker.py
openpyexcel/chart/picture.py
openpyexcel/chart/pie_chart.py
openpyexcel/chart/plotarea.py
openpyexcel/chart/print_settings.py
openpyexcel/chart/radar_chart.py
openpyexcel/chart/reader.py
openpyexcel/chart/reference.py
openpyexcel/chart/scatter_chart.py
openpyexcel/chart/series.py
openpyexcel/chart/series_factory.py
openpyexcel/chart/shapes.py
openpyexcel/chart/stock_chart.py
openpyexcel/chart/surface_chart.py
openpyexcel/chart/text.py
openpyexcel/chart/title.py
openpyexcel/chart/trendline.py
openpyexcel/chart/updown_bars.py
openpyexcel/chartsheet/__init__.py
openpyexcel/chartsheet/chartsheet.py
openpyexcel/chartsheet/custom.py
openpyexcel/chartsheet/properties.py
openpyexcel/chartsheet/protection.py
openpyexcel/chartsheet/publish.py
openpyexcel/chartsheet/relation.py
openpyexcel/chartsheet/views.py
openpyexcel/comments/__init__.py
openpyexcel/comments/author.py
openpyexcel/comments/comment_sheet.py
openpyexcel/comments/comments.py
openpyexcel/comments/shape_writer.py
openpyexcel/compat/__init__.py
openpyexcel/compat/abc.py
openpyexcel/compat/accumulate.py
openpyexcel/compat/numbers.py
openpyexcel/compat/singleton.py
openpyexcel/compat/strings.py
openpyexcel/descriptors/__init__.py
openpyexcel/descriptors/base.py
openpyexcel/descriptors/excel.py
openpyexcel/descriptors/namespace.py
openpyexcel-2.5.14.dist-info/LICENCE.rst
openpyexcel-2.5.14.dist-info/METADATA
openpyexcel-2.5.14.dist-info/WHEEL
openpyexcel-2.5.14.dist-info/top_level.txt
openpyexcel-2.5.14.dist-info/RECORD
