Metadata-Version: 1.2
Name: openpyexcel
Version: 2.5.14
Summary: A Python library to read/write Excel 2010 xlsx/xlsm files
Home-page: https://openpyxl.readthedocs.io
Author: See AUTHORS
Author-email: info@sciris.org
License: MIT/Expat
Project-URL: Documentation, https://openpyxl.readthedocs.io/en/stable/
Project-URL: Source, https://github.com/sciris/openpyexcel
Project-URL: Tracker, https://github.com/sciris/openpyexcel/issues
Platform: UNKNOWN
Classifier: Development Status :: 5 - Production/Stable
Classifier: Operating System :: MacOS :: MacOS X
Classifier: Operating System :: Microsoft :: Windows
Classifier: Operating System :: POSIX
Classifier: License :: OSI Approved :: MIT License
Classifier: Programming Language :: Python
Classifier: Programming Language :: Python :: 2.7
Classifier: Programming Language :: Python :: 3.4
Classifier: Programming Language :: Python :: 3.5
Classifier: Programming Language :: Python :: 3.6
Classifier: Programming Language :: Python :: 3.7
Requires-Python: >=2.7, !=3.0.*, !=3.1.*, !=3.2.*, !=3.3.*
